{"type":"Design","zone":null,"children":[{"type":"Page","properties":{"id":"page1","theme":"e"},"children":[{"type":"Header","zone":"top","properties":{"text":"ASSIGNMENT","position":"fixed","theme":"e"}},{"type":"Content","zone":"content"},{"type":"Footer","zone":"bottom","properties":{"position":"fixed"},"children":[{"type":"Navbar","children":[{"type":"Button","properties":{"text":"Home","icon":"home","target":"#page1"}},{"type":"Button","properties":{"text":"Menu","icon":"grid","target":"#page2"}},{"type":"Button","properties":{"text":"INFO","icon":"gear","target":"#page7"}}]}]}]},{"type":"Page","properties":{"theme":"e","id":"page2"},"children":[{"type":"Header","zone":"top","properties":{"text":"ASSIGNMENT","position":"fixed","theme":"e"}},{"type":"Content","zone":"content","children":[{"type":"List","children":[{"type":"ListButton","properties":{"text":"Pendahuluan","target":"#page3"}},{"type":"ListButton","properties":{"text":"Pengertian","target":"#page4"}},{"type":"ListButton","properties":{"text":"Kegiatan Belajar","target":"#page5"}},{"type":"ListButton","properties":{"text":"Video Tutorial","target":"#page8"}},{"type":"ListButton","properties":{"text":"Latihan","target":"#page6"}}]}]},{"type":"Footer","zone":"bottom","properties":{"position":"fixed"},"children":[{"type":"Navbar","children":[{"type":"Button","properties":{"text":"Home","icon":"home","target":"#page1"}},{"type":"Button","properties":{"text":"Menu","icon":"grid","target":"#page2"}},{"type":"Button","properties":{"text":"INFO","icon":"gear","target":"#page7"}}]}]}]},{"type":"Page","properties":{"theme":"e","id":"page3"},"children":[{"type":"Header","zone":"top","properties":{"text":"PENDAHULUAN","position":"fixed","theme":"e"},"children":[{"type":"Button","zone":"left","properties":{"text":"Back","icon":"arrow-l","target":"#page2"}}]},{"type":"Content","zone":"content","children":[{"type":"Text","properties":{"text":"Tujuan Pembelajaran :","type":"h2"}},{"type":"Text","properties":{"type":"p","text":"Peserta dapat menjelaskan bagaimana cara menggunakan \"ASSIGNMENT\" di moodle"}},{"type":"Text","properties":{"type":"p","text":"Kegiatan Belajar : Tutorial membuat assignment"}}]},{"type":"Footer","zone":"bottom","properties":{"position":"fixed"},"children":[{"type":"Navbar","children":[{"type":"Button","properties":{"text":"Home","icon":"home","target":"#page1"}},{"type":"Button","properties":{"text":"Menu","icon":"grid","target":"#page2"}},{"type":"Button","properties":{"text":"INFO","icon":"gear","target":"#page7"}}]}]}]},{"type":"Page","properties":{"theme":"e","id":"page4"},"children":[{"type":"Header","zone":"top","properties":{"text":"PENGERTIAN","position":"fixed","theme":"e"},"children":[{"type":"Button","zone":"left","properties":{"text":"Back","icon":"arrow-l","target":"#page2"}}]},{"type":"Content","zone":"content","children":[{"type":"Text","properties":{"text":"Assignment digunakan untuk menangani tugas mahasiswa secara online. Uraian tugas, cara pengumpulan (submission), deadline, penilaian","type":"p"}}]},{"type":"Footer","zone":"bottom","properties":{"position":"fixed"},"children":[{"type":"Navbar","children":[{"type":"Button","properties":{"text":"Home","icon":"home","target":"#page1"}},{"type":"Button","properties":{"text":"Menu","icon":"grid","target":"#page2"}},{"type":"Button","properties":{"text":"INFO","icon":"gear","target":"#page7"}}]}]}]},{"type":"Page","properties":{"theme":"e","id":"page5"},"children":[{"type":"Header","zone":"top","properties":{"text":"ASSIGNMENT","position":"fixed","theme":"e"},"children":[{"type":"Button","zone":"left","properties":{"text":"Back","target":"#page2","icon":"back"}}]},{"type":"Content","zone":"content","children":[{"type":"Text","properties":{"text":"Langkah - Langkah Pembuatan Assignment :","type":"h2"}},{"type":"Text","properties":{"text":"Dengan memilih "}},{"type":"Image","properties":{"src":"images/a.png"}},{"type":"Text","properties":{"text":"dilanjutkan denga klik "}}]},{"type":"Footer","zone":"bottom","properties":{"position":"fixed"},"children":[{"type":"Navbar","children":[{"type":"Button","properties":{"text":"Home","target":"#page1","icon":"home"}},{"type":"Button","properties":{"text":"Menu","target":"#page2","icon":"grid"}},{"type":"Button","properties":{"text":"INFO","icon":"gear"}}]}]}]},{"type":"Page","properties":{"theme":"e","id":"page6"},"children":[{"type":"Header","zone":"top","properties":{"text":"LATIHAN SOAL","position":"fixed","theme":"e"}},{"type":"Content","zone":"content"},{"type":"Footer","zone":"bottom","properties":{"position":"fixed"},"children":[{"type":"Navbar","children":[{"type":"Button","properties":{"text":"Home","target":"#page1","icon":"home"}},{"type":"Button","properties":{"text":"Menu","target":"#page2","icon":"grid"}},{"type":"Button","properties":{"text":"INFO","icon":"gear","target":"#page7"}}]}]}]},{"type":"Page","properties":{"dialog":true,"id":"page7"},"children":[{"type":"Header","zone":"top","properties":{"text":"About Us","position":"fixed"}},{"type":"Content","zone":"content","children":[{"type":"Text","properties":{"text":"Profil Penulis","type":"h2"}},{"type":"Text","properties":{"type":"p","text":"Nama Lengkap : Agnes Resama Robby"}},{"type":"Text","properties":{"text":"Tempat Tanggal Lahir : Malang, 27 Mei 1994","type":"p"}},{"type":"Image","properties":{"src":"images/DSC00530.JPG","width":200,"height":200,"align":"center"}}]}]},{"type":"Page","properties":{"theme":"e","id":"page8"},"children":[{"type":"Header","zone":"top","properties":{"text":"Video Tutorial","position":"fixed","theme":"e"},"children":[{"type":"Button","zone":"left","properties":{"text":"Back","target":"#page2","icon":"back"}}]},{"type":"Content","zone":"content","children":[{"type":"Text","properties":{"text":"Langkah - Langkah Pembuatan Assignment :","type":"h2"}},{"type":"Text","properties":{"text":"Dengan memilih "}},{"type":"Image","properties":{"src":"images/a.png"}},{"type":"Text","properties":{"text":"dilanjutkan denga klik "}}]},{"type":"Footer","zone":"bottom","properties":{"position":"fixed"},"children":[{"type":"Navbar","children":[{"type":"Button","properties":{"text":"Home","target":"#page1","icon":"home"}},{"type":"Button","properties":{"text":"Menu","target":"#page2","icon":"grid"}},{"type":"Button","properties":{"text":"INFO","icon":"gear"}}]}]}]}],"pInfo":{"name":"UAS","accessDate":1451876015366,"device":{"name":"Phones","screenWidth":320,"screenHeight":480,"rotating":false},"theme":"Default"}}